{
  "lastUpdated": "2026-02-08T10:04:29.830042-07:00",
  "items": [
    {
      "emoji": "\ud83c\udf93",
      "title": "Two Illinois Students Win National Diversity Leadership Scholarships",
      "summary": "",
      "url": "https://vetmed.illinois.edu/2026/02/06/two-illinois-students-win-national-diversity-leadership-scholarships/",
      "source": "Illinois Vet Med",
      "date": "2026-02-06"
    },
    {
      "emoji": "\ud83c\udf93",
      "title": "PVM Interview Days Move College Closer to Admitting the DVM Class of 2030",
      "summary": "",
      "url": "https://vet.purdue.edu/news/pvm-interview-days-move-college-closer-to-admitting-the-dvm-class-of-2030.php",
      "source": "Purdue University",
      "date": ""
    },
    {
      "emoji": "\ud83d\udcc5",
      "title": "Experts to Gather at Purdue for Conference Addressing the Public Health Threat of Antimicrobial Resi",
      "summary": "",
      "url": "https://vet.purdue.edu/news/experts-to-gather-at-purdue-for-conference-addressing-the-public-health-threat-of-antimicrobial-resistance.php",
      "source": "Purdue University",
      "date": ""
    },
    {
      "emoji": "\ud83d\udc15",
      "title": "PVM\u2019s Upcoming Coppoc One Health Lecture to Focus on Dogs as Sentinels of Environmental Exposure",
      "summary": "",
      "url": "https://vet.purdue.edu/news/pvms-upcoming-coppoc-one-health-lecture-to-focus-on-dogs-as-sentinels-of-environmental-exposure.php",
      "source": "Purdue University",
      "date": ""
    },
    {
      "emoji": "\ud83c\udf93",
      "title": "Oxford Scholar Awarded Prestigious NIH Fellowship",
      "summary": "",
      "url": "https://headlines.liu.edu/oxford-scholar-awarded-prestigious-nih-fellowship/",
      "source": "Long Island University",
      "date": "2026-02-06"
    },
    {
      "emoji": "\ud83d\udcb0",
      "title": "National Foundation Funds Vet Professor\u2019s New Research",
      "summary": "",
      "url": "https://headlines.liu.edu/national-foundation-funds-vet-professors-new-research/",
      "source": "Long Island University",
      "date": "2026-02-06"
    },
    {
      "emoji": "\ud83e\udd1d",
      "title": "Mississippi State University College of Veterinary Medicine announces new partnership with Loop Abro",
      "summary": "",
      "url": "https://www.msstate.edu/newsroom/article/2025/12/mississippi-state-university-college-veterinary-medicine-announces-new",
      "source": "Mississippi State University",
      "date": ""
    },
    {
      "emoji": "\ud83d\udd2c",
      "title": "Mississippi State breaks ground for Nancy Fair Link Laminitis Research Center to combat disease in p",
      "summary": "",
      "url": "https://www.msstate.edu/newsroom/article/2025/11/mississippi-state-breaks-ground-nancy-fair-link-laminitis-research-center",
      "source": "Mississippi State University",
      "date": ""
    },
    {
      "emoji": "\ud83d\udcf0",
      "title": "MSU faculty named SEC Academic Leadership Development Program Fellows",
      "summary": "",
      "url": "https://www.msstate.edu/newsroom/article/2025/10/msu-faculty-named-sec-academic-leadership-development-program-fellows",
      "source": "Mississippi State University",
      "date": ""
    },
    {
      "emoji": "\ud83d\udd2c",
      "title": "UN highlights MSU\u2019s aquatic food research at FAO World Food Forum",
      "summary": "",
      "url": "https://www.msstate.edu/newsroom/article/2025/10/un-highlights-msus-aquatic-food-research-fao-world-food-forum",
      "source": "Mississippi State University",
      "date": ""
    },
    {
      "emoji": "\ud83d\udcf0",
      "title": "U.S. Secretary of Agriculture Rollins announces Rural Veterinary Action Plan during visit to Mississ",
      "summary": "",
      "url": "https://www.msstate.edu/newsroom/article/2025/08/us-secretary-agriculture-rollins-announces-rural-veterinary-action-plan",
      "source": "Mississippi State University",
      "date": ""
    },
    {
      "emoji": "\ud83e\udd16",
      "title": "Marketing Chair, Engineer Talk Memory Chips with Financial Post",
      "summary": "",
      "url": "https://news.uoguelph.ca/2026/02/marketing-chair-engineer-talk-memory-chips-with-financial-post/?utm_source=rss&utm_medium=rss&utm_campaign=marketing-chair-engineer-talk-memory-chips-with-financial-post",
      "source": "University of Guelph",
      "date": "2026-02-06"
    },
    {
      "emoji": "\ud83c\udfc6",
      "title": "Roman Ganta selected as ACVM Honorary Member",
      "summary": "",
      "url": "https://cvm.missouri.edu/roman-ganta-selected-as-acvm-honorary-member/",
      "source": "Missouri Vet Med",
      "date": "2026-02-06"
    },
    {
      "emoji": "\ud83d\udcb0",
      "title": "UC Davis Receives $120M Gift, Largest Ever to Veterinary Medicine",
      "summary": "",
      "url": "https://www.ucdavis.edu/news/uc-davis-receives-120m-gift-largest-ever-veterinary-medicine",
      "source": "UC Davis",
      "date": ""
    },
    {
      "emoji": "\ud83d\udcf0",
      "title": "Riverside University Health System to offer podiatric residency led by WesternU CPM faculty",
      "summary": "",
      "url": "https://www.westernu.edu/riverside-university-health-system-to-offer-podiatric-residency-led-by-westernu-cpm-faculty/",
      "source": "Western University",
      "date": "2026-01-23"
    },
    {
      "emoji": "\ud83d\udd2c",
      "title": "Collaboration drives innovation at the 11th\u00a0annual\u00a0WesternU\u00a0Oregon\u00a0Research\u00a0Symposium",
      "summary": "",
      "url": "https://www.westernu.edu/collaboration-drives-innovation-at-the-11th-annual-westernu-oregon-research-symposium/",
      "source": "Western University",
      "date": "2026-01-21"
    },
    {
      "emoji": "\ud83c\udf93",
      "title": "WesternU COMP continues to grow its annual student research symposium",
      "summary": "",
      "url": "https://www.westernu.edu/westernu-comp-continues-to-grow-its-annual-student-research-symposium/",
      "source": "Western University",
      "date": "2025-12-20"
    },
    {
      "emoji": "\ud83d\udcc5",
      "title": "WesternU\u2019s\u00a0One Health Symposium\u00a0highlights\u00a0connections\u00a0between\u00a0animal, human, and environmental heal",
      "summary": "",
      "url": "https://www.westernu.edu/westernus-one-health-symposium-highlights-connections-between-animal-human-and-environmental-health/",
      "source": "Western University",
      "date": "2025-12-15"
    },
    {
      "emoji": "\ud83d\udcf0",
      "title": "LMU Grows Its Footprint with Major Medical and Veterinary Expansion in Orange Park, Florida",
      "summary": "",
      "url": "https://www.lmunet.edu/news/2025/12/Major-Medical-and-Veterinary-Expansion-in-Orange-Park.php",
      "source": "Lincoln Memorial University",
      "date": ""
    },
    {
      "emoji": "\ud83d\udcf0",
      "title": "Kadidia Toure Named USBWA National Player of the Week",
      "summary": "",
      "url": "https://headlines.liu.edu/kadidia-toure-named-usbwa-national-player-of-the-week/",
      "source": "Long Island University",
      "date": "2026-01-31"
    },
    {
      "emoji": "\ud83c\udf93",
      "title": "Nine Students Selected to Present at National Conference",
      "summary": "",
      "url": "https://headlines.liu.edu/nine-students-selected-to-present-at-national-conference/",
      "source": "Long Island University",
      "date": "2026-01-23"
    },
    {
      "emoji": "\ud83d\udd2c",
      "title": "WSU researchers say studying pig and grizzly bear skin may unlock new anti-aging, scar repair therap",
      "summary": "",
      "url": "https://vetmed.wsu.edu/wsu-researchers-say-studying-pig-and-grizzly-bear-skin-may-unlock-new-anti-aging-scar-repair-therapies/",
      "source": "Washington State Vet Med",
      "date": "2026-02-05"
    },
    {
      "emoji": "\ud83d\udcf0",
      "title": "UPEI officially opens the new Faculty of Medicine and Health Sciences Centre",
      "summary": "",
      "url": "https://www.upei.ca/communications/news/2025/11/upei-officially-opens-new-faculty-medicine-and-health-sciences-centre",
      "source": "UPEI Atlantic Veterinary College",
      "date": "2025-11-28"
    },
    {
      "emoji": "\ud83d\udd2c",
      "title": "UPEI Canada Research Chair in Socio-Psychological Epidemiology for Healthy Animals renewed",
      "summary": "",
      "url": "https://www.upei.ca/communications/news/2025/11/upei-canada-research-chair-socio-psychological-epidemiology-healthy",
      "source": "UPEI Atlantic Veterinary College",
      "date": "2025-11-04"
    },
    {
      "emoji": "\ud83c\udf93",
      "title": "Tufts Theriogenology Club and Student Livestock Organization Bovine Breeding Lab",
      "summary": "",
      "url": "https://vet.tufts.edu/news-events/news/tufts-theriogenology-club-and-student-livestock-organization-bovine-breeding-lab",
      "source": "Tufts University",
      "date": "2026-02-05"
    },
    {
      "emoji": "\ud83d\udcf0",
      "title": "LSU Vet Med to host annual Open House",
      "summary": "",
      "url": "https://www.lsu.edu/vetmed/news/2026/open_house.php",
      "source": "Louisiana State University",
      "date": ""
    },
    {
      "emoji": "\ud83d\udc04",
      "title": "Winter weather tips for pet and livestock owners",
      "summary": "",
      "url": "https://www.lsu.edu/vetmed/news/2026/winter_weather_tips.php",
      "source": "Louisiana State University",
      "date": ""
    },
    {
      "emoji": "\ud83d\udcf0",
      "title": "LSU Vet Med to release bald eagle on Thursday, January 1 in South Toledo Bend State Park",
      "summary": "",
      "url": "https://www.lsu.edu/vetmed/news/2025/eagle_toledo_bend.php",
      "source": "Louisiana State University",
      "date": ""
    },
    {
      "emoji": "\ud83d\udd2c",
      "title": "LSU Vet Med researchers investigating Equine herpesvirus",
      "summary": "",
      "url": "https://www.lsu.edu/vetmed/news/2025/equine_herpesvirus_research.php",
      "source": "Louisiana State University",
      "date": ""
    },
    {
      "emoji": "\ud83c\udf93",
      "title": "LSU School of Veterinary Medicine conferred two advanced degrees",
      "summary": "",
      "url": "https://www.lsu.edu/vetmed/news/2025/graduation_fall2025.php",
      "source": "Louisiana State University",
      "date": ""
    },
    {
      "emoji": "\ud83d\udcf0",
      "title": "Roy named director of LSU Diagnostics",
      "summary": "",
      "url": "https://www.lsu.edu/vetmed/news/2025/lsudx_director.php",
      "source": "Louisiana State University",
      "date": ""
    },
    {
      "emoji": "\ud83d\udc34",
      "title": "LSU Vet Med treating three Texas horses quarantined for confirmed Equine Herpesvirus-1",
      "summary": "",
      "url": "https://www.lsu.edu/vetmed/news/2025/equine_herpesvirus.php",
      "source": "Louisiana State University",
      "date": ""
    },
    {
      "emoji": "\ud83c\udfc6",
      "title": "Winners announced for LSU Vet Med's 31st Annual International Exhibition on Animals in Art",
      "summary": "",
      "url": "https://www.lsu.edu/vetmed/news/2025/art_awards.php",
      "source": "Louisiana State University",
      "date": ""
    },
    {
      "emoji": "\ud83d\udcf0",
      "title": "LSU Vet Med opens International Exhibition on Animals in Art on October 4 with reception",
      "summary": "",
      "url": "https://www.lsu.edu/vetmed/news/2025/animals_in_art.php",
      "source": "Louisiana State University",
      "date": ""
    },
    {
      "emoji": "\ud83d\udcb0",
      "title": "LSU Vet Med honors endowed professors whose work impacts animal and human health every day",
      "summary": "",
      "url": "https://www.lsu.edu/vetmed/news/2025/professorships.php",
      "source": "Louisiana State University",
      "date": ""
    },
    {
      "emoji": "\ud83c\udf93",
      "title": "Student blog: Stepping through the gates of zoo medicine",
      "summary": "",
      "url": "https://www.vet.cornell.edu/about-us/news/20260205/student-blog-stepping-through-gates-zoo-medicine",
      "source": "Cornell University",
      "date": ""
    },
    {
      "emoji": "\ud83c\udf93",
      "title": "Cornell Public Health announces new, full-tuition fellowship",
      "summary": "",
      "url": "https://www.vet.cornell.edu/about-us/news/20260205/cornell-public-health-announces-new-full-tuition-fellowship",
      "source": "Cornell University",
      "date": ""
    },
    {
      "emoji": "\ud83d\udc15",
      "title": "Boiler Up, Basketball and a Dog Named Walter Put Purdue Veterinary Medicine in TV Spotlight",
      "summary": "",
      "url": "https://vet.purdue.edu/news/boiler-up-basketball-and-a-dog-named-walter-put-purdue-veterinary-medicine-in-tv-spotlight.php",
      "source": "Purdue University",
      "date": ""
    },
    {
      "emoji": "\ud83d\udc34",
      "title": "Annual PVM Equine Wellness Forum February 7 Features Enlightening Horse Health Presentations and Dem",
      "summary": "",
      "url": "https://vet.purdue.edu/news/annual-pvm-equine-wellness-forum-february-7-features-enlightening-horse-health-presentations-and-demonstrations.php",
      "source": "Purdue University",
      "date": ""
    },
    {
      "emoji": "\ud83e\udd1d",
      "title": "History in the Making: Purdue Veterinary Medicine Connects 21st Century Diagnostic Imaging with Preh",
      "summary": "",
      "url": "https://vet.purdue.edu/news/pvr25-history-in-the-making.php",
      "source": "Purdue University",
      "date": ""
    },
    {
      "emoji": "\ud83c\udf93",
      "title": "Carrying Forward a Life of Care: Family Honors Memory of Purdue Graduate Dr. Rick Chaille with Suppo",
      "summary": "",
      "url": "https://vet.purdue.edu/news/pvr25-carrying-forward-a-life-of-care-family-honors-memory-of-purdue-graduate-dr-rick-chaille-with-support-for-purdue-veterinary-hospitals-nutrition-kitchen.php",
      "source": "Purdue University",
      "date": ""
    },
    {
      "emoji": "\ud83c\udf93",
      "title": "PVM Scholars Co-Edit New Edition of Signature Veterinary Histology Textbook",
      "summary": "",
      "url": "https://vet.purdue.edu/news/pvr25-pvm-scholars-co-edit-new-edition-of-signature-veterinary-histology-textbook.php",
      "source": "Purdue University",
      "date": ""
    },
    {
      "emoji": "\ud83d\udc89",
      "title": "Electric Signals Help Immune Cells Find Their Way",
      "summary": "",
      "url": "https://vet.purdue.edu/news/pvr25-electric-signals-help-immune-cells-find-their-way.php",
      "source": "Purdue University",
      "date": ""
    },
    {
      "emoji": "\ud83d\udcf0",
      "title": "Welcome New Faculty",
      "summary": "",
      "url": "https://vet.purdue.edu/news/pvr25-welcome-new-faculty.php",
      "source": "Purdue University",
      "date": ""
    },
    {
      "emoji": "\ud83e\udd81",
      "title": "Leading The Flock: Texas A&M Epidemiologist Studies Zoonotic Diseases\u2019 Impact On Animals, People",
      "summary": "",
      "url": "https://vetmed.tamu.edu/news/press-releases/leading-the-flock-zoonotic-disease-research/",
      "source": "Texas A&M",
      "date": ""
    },
    {
      "emoji": "\ud83d\udd2c",
      "title": "COWGIRL Honors VMBS Faculty Member, Researcher",
      "summary": "",
      "url": "https://vetmed.tamu.edu/news/press-releases/cowgirl-honors-vmbs-faculty-member-researcher/",
      "source": "Texas A&M",
      "date": ""
    },
    {
      "emoji": "\ud83d\udc15",
      "title": "Learning Through Duke: How Texas A&M Helped One Family Understand And Manage Canine Diabetes",
      "summary": "",
      "url": "https://vetmed.tamu.edu/news/press-releases/learning-through-duke-canine-diabetes-texas-am/",
      "source": "Texas A&M",
      "date": ""
    },
    {
      "emoji": "\ud83d\udd2c",
      "title": "VERO Researcher Recognized For Contributions To Food Animal Medicine",
      "summary": "",
      "url": "https://vetmed.tamu.edu/news/press-releases/vero-researcher-recognized-food-animal-medicine/",
      "source": "Texas A&M",
      "date": ""
    },
    {
      "emoji": "\ud83c\udfe5",
      "title": "Facility Grand Opening Lauds New Horizons in Health Care, Veterinary Medicine Education for Rio Gran",
      "summary": "",
      "url": "https://vetmed.tamu.edu/news/press-releases/mcallen-facility-expands-health-care-veterinary-medicine/",
      "source": "Texas A&M",
      "date": ""
    },
    {
      "emoji": "\ud83d\udcf0",
      "title": "Protecting Animals, Plants, and Pipes From Winter Weather",
      "summary": "",
      "url": "https://vetmed.tamu.edu/news/homepage/winter-weather-tips-for-animals-plants-and-pipes/",
      "source": "Texas A&M",
      "date": ""
    },
    {
      "emoji": "\ud83d\udd2c",
      "title": "Texas A&M Research Team Identifies Species Of Brucellosis-Causing Bacteria In Cameroon",
      "summary": "",
      "url": "https://vetmed.tamu.edu/news/press-releases/brucellosis-in-cameroon/",
      "source": "Texas A&M",
      "date": ""
    },
    {
      "emoji": "\ud83c\udf93",
      "title": "Aggie Veterinary Student Pursues Career Goals With Help From Biomedical Sciences Master\u2019s Degree",
      "summary": "",
      "url": "https://vetmed.tamu.edu/news/press-releases/brianna-bazel/",
      "source": "Texas A&M",
      "date": ""
    },
    {
      "emoji": "\ud83e\udd57",
      "title": "Bridging Gaps In Veterinary Medicine: Texas A&M Gains New Food Animal Faculty Member",
      "summary": "",
      "url": "https://vetmed.tamu.edu/news/press-releases/jake-trautmann/",
      "source": "Texas A&M",
      "date": ""
    },
    {
      "emoji": "\ud83d\udd2c",
      "title": "From the lab to the NICU: UW researchers pioneer contactless health monitoring",
      "summary": "",
      "url": "https://cdis.wisc.edu/uw-madison-researchers-pioneer-contactless-health-monitoring/",
      "source": "University of Wisconsin",
      "date": "2026-01-29"
    },
    {
      "emoji": "\ud83d\udcf0",
      "title": "Molecular messengers: Decoding a circulatory threat",
      "summary": "",
      "url": "https://www.vetmed.auburn.edu/blog/cvm-news/molecular-messengers-decoding-a-circulatory-threat/",
      "source": "Auburn University",
      "date": ""
    },
    {
      "emoji": "\ud83e\udd81",
      "title": "Spotlighting the CVM\u2019s unique exotics experiences",
      "summary": "",
      "url": "https://www.vetmed.auburn.edu/blog/cvm-news/spotlighting-the-cvms-unique-exotics-experiences/",
      "source": "Auburn University",
      "date": ""
    },
    {
      "emoji": "\ud83d\udcf0",
      "title": "Internship program helps address shortage of veterinary technicians",
      "summary": "",
      "url": "https://wire.auburn.edu/content/ocm/2026/01/201622-vet-tech-program.php",
      "source": "Auburn University",
      "date": ""
    },
    {
      "emoji": "\ud83c\udfe5",
      "title": "Department of Clinical Sciences earns Excellence in Education Award",
      "summary": "",
      "url": "https://wire.auburn.edu/content/announcements/2026/01/09120136-announcement.php",
      "source": "Auburn University",
      "date": ""
    },
    {
      "emoji": "\ud83c\udf93",
      "title": "Public and One Health student turns curiosity into impact",
      "summary": "",
      "url": "https://www.vetmed.auburn.edu/blog/cvm-news/public-and-one-health-student-turns-curiosity-into-impact/",
      "source": "Auburn University",
      "date": ""
    },
    {
      "emoji": "\ud83c\udf93",
      "title": "Global perspectives: Cottingham selected for NCURA fellowship",
      "summary": "",
      "url": "https://www.vetmed.auburn.edu/blog/cvm-news/global-perspectives-cottingham-selected-for-ncura-fellowship/",
      "source": "Auburn University",
      "date": ""
    },
    {
      "emoji": "\ud83c\udf93",
      "title": "Roots in horse capital inspire Auburn DVM student",
      "summary": "",
      "url": "https://www.vetmed.auburn.edu/blog/cvm-news/roots-in-horse-capital-inspire-auburn-dvm-student/",
      "source": "Auburn University",
      "date": ""
    },
    {
      "emoji": "\ud83d\udc15",
      "title": "CVM to create professorship focusing on feline, canine nutrition",
      "summary": "",
      "url": "https://www.vetmed.auburn.edu/blog/cvm-news/cvm-to-create-professorship-focusing-on-feline-canine-nutrition/",
      "source": "Auburn University",
      "date": ""
    },
    {
      "emoji": "\ud83d\udea8",
      "title": "Hope in action: Veterinary medicine professor launches emergency rescue team",
      "summary": "",
      "url": "https://wire.auburn.edu/content/philanthropy/2025/11/241000-avert.php",
      "source": "Auburn University",
      "date": ""
    },
    {
      "emoji": "\ud83d\udcf0",
      "title": "University Mourns Passing of Faculty Member",
      "summary": "",
      "url": "https://news.uoguelph.ca/2026/02/university-mourns-passing-of-faculty-member-7/?utm_source=rss&utm_medium=rss&utm_campaign=university-mourns-passing-of-faculty-member-7",
      "source": "University of Guelph",
      "date": "2026-02-05"
    },
    {
      "emoji": "\ud83d\udc34",
      "title": "Diagnosing and Treating Equine Vitamin E Deficiency Diseases",
      "summary": "",
      "url": "https://thehorse.com/1142250/diagnosing-and-treating-equine-vitamin-e-deficiency-diseases/",
      "source": "University of Pennsylvania",
      "date": "2026-02-04"
    },
    {
      "emoji": "\ud83e\udd16",
      "title": "How to Help Your Pet Maintain a Healthy Weight",
      "summary": "",
      "url": "https://news.uoguelph.ca/2026/02/how-to-help-your-pet-maintain-a-healthy-weight/?utm_source=rss&utm_medium=rss&utm_campaign=how-to-help-your-pet-maintain-a-healthy-weight",
      "source": "University of Guelph",
      "date": "2026-02-04"
    },
    {
      "emoji": "\ud83e\udd57",
      "title": "Where food safety meets veterinary medicine",
      "summary": "",
      "url": "https://cvm.missouri.edu/where-food-safety-meets-veterinary-medicine/",
      "source": "Missouri Vet Med",
      "date": "2026-02-05"
    },
    {
      "emoji": "\ud83d\udd2c",
      "title": "Skeletal muscle research focuses on improving health span",
      "summary": "",
      "url": "https://news.okstate.edu/articles/veterinary-medicine/2025/butcher_research.html",
      "source": "Oklahoma State University",
      "date": ""
    },
    {
      "emoji": "\ud83c\udf93",
      "title": "CVM appoints Dr. David Renter as associate dean for research and graduate programs",
      "summary": "",
      "url": "https://www.vet.k-state.edu/about/news-events-publications/lifelines/2601.html#Renter",
      "source": "Kansas State University",
      "date": ""
    },
    {
      "emoji": "\ud83c\udf93",
      "title": "First-year student receives livestock scholarship",
      "summary": "",
      "url": "https://www.vet.k-state.edu/about/news-events-publications/lifelines/2601.html#Marchiano",
      "source": "Kansas State University",
      "date": ""
    },
    {
      "emoji": "\ud83d\udd2c",
      "title": "K-State research suggests obesity reduces influenza vaccine effectiveness in male animals",
      "summary": "",
      "url": "https://www.vet.k-state.edu/about/news-events-publications/lifelines/2601.html#obesity",
      "source": "Kansas State University",
      "date": ""
    },
    {
      "emoji": "\ud83c\udf93",
      "title": "Second-year student receives Lallemand Animal Nutrition scholarship",
      "summary": "",
      "url": "https://www.vet.k-state.edu/about/news-events-publications/lifelines/2601.html#Larson",
      "source": "Kansas State University",
      "date": ""
    },
    {
      "emoji": "\ud83d\udd2c",
      "title": "Research seeks to help children breathe easier and avoid respiratory infection",
      "summary": "",
      "url": "https://www.vet.k-state.edu/about/news-events-publications/lifelines/2601.html#Baral",
      "source": "Kansas State University",
      "date": ""
    },
    {
      "emoji": "\ud83c\udfc6",
      "title": "Veterinary college recognizes faculty with annual teaching awards",
      "summary": "",
      "url": "https://www.vet.k-state.edu/about/news-events-publications/lifelines/2511.html#Teaching",
      "source": "Kansas State University",
      "date": ""
    },
    {
      "emoji": "\ud83d\udcb0",
      "title": "A kind fund helps veterinary students in need during unkind situations",
      "summary": "",
      "url": "https://www.vet.k-state.edu/about/news-events-publications/lifelines/2511.html#NIK",
      "source": "Kansas State University",
      "date": ""
    },
    {
      "emoji": "\ud83d\udcf0",
      "title": "Dr. Stacy McHaney meets the press to talk about veterinary radiology",
      "summary": "",
      "url": "https://www.vet.k-state.edu/about/news-events-publications/lifelines/2511.html#McHaney",
      "source": "Kansas State University",
      "date": ""
    },
    {
      "emoji": "\ud83d\udcf0",
      "title": "Search committee for new Hodes Family Dean named",
      "summary": "",
      "url": "https://www.vet.k-state.edu/about/news-events-publications/lifelines/2511.html#Search",
      "source": "Kansas State University",
      "date": ""
    },
    {
      "emoji": "\ud83d\udcf0",
      "title": "Dr. Susan Nelson passes along several tips for pet safety at Thanksgiving and other holidays",
      "summary": "",
      "url": "https://www.vet.k-state.edu/about/news-events-publications/lifelines/2511.html#Thanksgiving",
      "source": "Kansas State University",
      "date": ""
    },
    {
      "emoji": "\ud83c\udf93",
      "title": "Fourth-year student receives prestigious Coyote Rock Canyon Scholarship",
      "summary": "",
      "url": "https://www.vet.k-state.edu/about/news-events-publications/lifelines/2510.html#Bolinger",
      "source": "Kansas State University",
      "date": ""
    },
    {
      "emoji": "\ud83d\udc31",
      "title": "Dr. Konnor Stueve dissects anatomy education to reach advanced learners",
      "summary": "",
      "url": "https://www.vet.k-state.edu/about/news-events-publications/lifelines/2510.html#Stueve",
      "source": "Kansas State University",
      "date": ""
    },
    {
      "emoji": "\ud83c\udf93",
      "title": "Veterinary students corral scholarship awards at AABP",
      "summary": "",
      "url": "https://www.vet.k-state.edu/about/news-events-publications/lifelines/2510.html#AABP",
      "source": "Kansas State University",
      "date": ""
    },
    {
      "emoji": "\ud83c\udf93",
      "title": "Equine specialists surprise fourth-year student with scholarship award at Vet Town",
      "summary": "",
      "url": "https://www.vet.k-state.edu/about/news-events-publications/lifelines/2510.html#Jokovick",
      "source": "Kansas State University",
      "date": ""
    },
    {
      "emoji": "\ud83d\udd2c",
      "title": "Research underscores complexity of treating bovine respiratory disease",
      "summary": "",
      "url": "https://www.vet.k-state.edu/about/news-events-publications/lifelines/2510.html#BRD",
      "source": "Kansas State University",
      "date": ""
    },
    {
      "emoji": "\ud83d\udcf0",
      "title": "Where have animals tested positive for rabies in Kansas?",
      "summary": "",
      "url": "https://www.vet.k-state.edu/about/news-events-publications/lifelines/2510.html#rabies",
      "source": "Kansas State University",
      "date": ""
    },
    {
      "emoji": "\ud83d\udcc5",
      "title": "Prevent Halloween pet scares with these tips from a K-State veterinarian",
      "summary": "",
      "url": "https://www.vet.k-state.edu/about/news-events-publications/lifelines/2510.html#Halloween",
      "source": "Kansas State University",
      "date": ""
    },
    {
      "emoji": "\ud83c\udfe5",
      "title": "Veterinary Health Center launches expanded, renovated small animal surgery center",
      "summary": "",
      "url": "https://www.vet.k-state.edu/about/news-events-publications/lifelines/2509.html#surgery",
      "source": "Kansas State University",
      "date": ""
    },
    {
      "emoji": "\ud83c\udf93",
      "title": "Three K-State veterinary students earn national Merck Animal Health scholarships",
      "summary": "",
      "url": "https://www.vet.k-state.edu/about/news-events-publications/lifelines/2509.html#Merck",
      "source": "Kansas State University",
      "date": ""
    },
    {
      "emoji": "\ud83c\udf93",
      "title": "Dr. Cody Dressler goes the extra mile to care for animals and lead students in the shelter medicine ",
      "summary": "",
      "url": "https://www.vet.k-state.edu/about/news-events-publications/lifelines/2509.html#Dressler",
      "source": "Kansas State University",
      "date": ""
    },
    {
      "emoji": "\ud83d\udd2c",
      "title": "New research at K-State swats back at mosquito-borne virus threatening pork industry",
      "summary": "",
      "url": "https://www.vet.k-state.edu/about/news-events-publications/lifelines/2509.html#Encephalitis",
      "source": "Kansas State University",
      "date": ""
    },
    {
      "emoji": "\ud83d\udc15",
      "title": "K-State veterinarians save at risk dog, now up for adoption",
      "summary": "",
      "url": "https://www.vet.k-state.edu/about/news-events-publications/lifelines/2509.html#Korah",
      "source": "Kansas State University",
      "date": ""
    },
    {
      "emoji": "\ud83c\udf93",
      "title": "Veterinary Medical Library offers internship program for students",
      "summary": "",
      "url": "https://www.vet.k-state.edu/about/news-events-publications/lifelines/2509.html#library",
      "source": "Kansas State University",
      "date": ""
    },
    {
      "emoji": "\ud83e\udd57",
      "title": "A critical shortage of veterinarians could threaten America\u2019s food supply",
      "summary": "",
      "url": "https://www.vet.k-state.edu/about/news-events-publications/lifelines/2509.html#supply",
      "source": "Kansas State University",
      "date": ""
    },
    {
      "emoji": "\ud83e\udd1d",
      "title": "K-State, Iowa State and University College Dublin sign veterinary medicine partnership in Ireland",
      "summary": "",
      "url": "https://www.vet.k-state.edu/about/news-events-publications/lifelines/2508.html#partnership",
      "source": "Kansas State University",
      "date": ""
    },
    {
      "emoji": "\ud83d\udc89",
      "title": "Investing in Kansas' first line of defense against animal disease",
      "summary": "",
      "url": "https://www.vet.k-state.edu/about/news-events-publications/lifelines/2508.html#defense",
      "source": "Kansas State University",
      "date": ""
    },
    {
      "emoji": "\ud83c\udf93",
      "title": "Summer veterinary research program pairs experienced mentors with students",
      "summary": "",
      "url": "https://www.vet.k-state.edu/about/news-events-publications/lifelines/2508.html#VRSP",
      "source": "Kansas State University",
      "date": ""
    },
    {
      "emoji": "\ud83d\udc31",
      "title": "Cattle Chat: Managing bulls between breeding seasons",
      "summary": "",
      "url": "https://www.vet.k-state.edu/about/news-events-publications/lifelines/2508.html#cattle",
      "source": "Kansas State University",
      "date": ""
    },
    {
      "emoji": "\ud83e\udd16",
      "title": "Kansas Veterinary Diagnostic Medicine internship program doubles number of trainees",
      "summary": "",
      "url": "https://www.vet.k-state.edu/about/news-events-publications/lifelines/2508.html#KVDL-interns",
      "source": "Kansas State University",
      "date": ""
    },
    {
      "emoji": "\ud83d\udd2c",
      "title": "Collaborative research in the Center of Outcomes Research and Epidemiology finds most dogs are vacci",
      "summary": "",
      "url": "https://www.vet.k-state.edu/about/news-events-publications/lifelines/2508.html#vaccinations",
      "source": "Kansas State University",
      "date": ""
    },
    {
      "emoji": "\ud83d\udcf0",
      "title": "Dr. Elizabeth Davis named interim dean as K-State bids farewell to Dr. Bonnie Rush",
      "summary": "",
      "url": "https://www.vet.k-state.edu/about/news-events-publications/lifelines/2507.html#Davis",
      "source": "Kansas State University",
      "date": ""
    },
    {
      "emoji": "\ud83d\udc31",
      "title": "Dr. Brad White uses expertise to support cattle industry and rural veterinary practice",
      "summary": "",
      "url": "https://www.vet.k-state.edu/about/news-events-publications/lifelines/2507.html#White",
      "source": "Kansas State University",
      "date": ""
    }
  ]
}